{
  "title": "汕头市澄海区美思琪玩具厂召回部分美思琪牌过家家玩具，涉及数量为200只",
  "link": "https://cj.sina.com.cn/articles/view/1704103183/65928d0f02007wd6i",
  "time": "金融界网站   2025-05-14 19:16:27",
  "platform": "新浪新闻",
  "type": "通知",
  "摘要": "美思琪玩具召回涉安全隐患,",
  "四元组": [
    {
      "实体1": "汕头市澄海区美思琪玩具厂",
      "事件": "召回",
      "实体2": "美思琪牌过家家玩具",
      "情感": "负面"
    },
    {
      "实体1": "美思琪牌过家家玩具",
      "事件": "存在安全隐患",
      "实体2": "儿童",
      "情感": "负面"
    },
    {
      "实体1": "汕头市澄海区美思琪玩具厂",
      "事件": "提供",
      "实体2": "免费退货服务",
      "情感": "正面"
    }
  ]
}